comfy_ui_mcp_server/__init__.py
comfy_ui_mcp_server/server.py
comfy_ui_mcp_server-0.1.0.dist-info/METADATA
comfy_ui_mcp_server-0.1.0.dist-info/WHEEL
comfy_ui_mcp_server-0.1.0.dist-info/entry_points.txt
comfy_ui_mcp_server-0.1.0.dist-info/licenses/LICENSE
comfy_ui_mcp_server-0.1.0.dist-info/RECORD
